tmtoolkit/__init__.py
tmtoolkit/__main__.py
tmtoolkit/ngrammodels.py
tmtoolkit/strings.py
tmtoolkit/types.py
tmtoolkit/utils.py
tmtoolkit/bow/__init__.py
tmtoolkit/bow/_naivebayes.py
tmtoolkit/bow/bow_stats.py
tmtoolkit/bow/dtm.py
tmtoolkit/corpus/__init__.py
tmtoolkit/corpus/_common.py
tmtoolkit/corpus/_corpus.py
tmtoolkit/corpus/_corpusfuncs.py
tmtoolkit/corpus/_document.py
tmtoolkit/corpus/_nltk_extras.py
tmtoolkit/corpus/visualize.py
tmtoolkit/data/de/parlspeech-v2-sample-bundestag.zip
tmtoolkit/data/en/News100.zip
tmtoolkit/data/en/NewsArticles.zip
tmtoolkit/data/en/healthtweets.zip
tmtoolkit/data/en/parlspeech-v2-sample-houseofcommons.zip
tmtoolkit/data/es/parlspeech-v2-sample-congreso.zip
tmtoolkit/data/nl/parlspeech-v2-sample-tweedekamer.zip
tmtoolkit/tokenseq/__init__.py
tmtoolkit/tokenseq/_metrics.py
tmtoolkit/topicmod/__init__.py
tmtoolkit/topicmod/_common.py
tmtoolkit/topicmod/_eval_tools.py
tmtoolkit/topicmod/evaluate.py
tmtoolkit/topicmod/model_io.py
tmtoolkit/topicmod/model_stats.py
tmtoolkit/topicmod/parallel.py
tmtoolkit/topicmod/tm_gensim.py
tmtoolkit/topicmod/tm_lda.py
tmtoolkit/topicmod/tm_sklearn.py
tmtoolkit/topicmod/visualize.py
tmtoolkit-0.12.0.dist-info/AUTHORS.md
tmtoolkit-0.12.0.dist-info/LICENSE
tmtoolkit-0.12.0.dist-info/METADATA
tmtoolkit-0.12.0.dist-info/WHEEL
tmtoolkit-0.12.0.dist-info/top_level.txt
tmtoolkit-0.12.0.dist-info/RECORD
