Metadata-Version: 2.1
Name: tmtoolkit
Version: 0.12.0
Summary: Text Mining and Topic Modeling Toolkit
Home-page: https://github.com/internaut/tmtoolkit
Author: Markus Konrad
Author-email: post@mkonrad.net
License: Apache License 2.0
Project-URL: Bug Reports, https://github.com/internaut/tmtoolkit/issues
Project-URL: Source, https://github.com/internaut/tmtoolkit
Keywords: textmining textanalysis text mining analysis preprocessing topicmodeling topic modeling evaluation
Classifier: Development Status :: 4 - Beta
Classifier: Intended Audience :: Science/Research
Classifier: Intended Audience :: Developers
Classifier: License :: OSI Approved :: Apache Software License
Classifier: Operating System :: OS Independent
Classifier: Programming Language :: Python
Classifier: Programming Language :: Python :: 3
Classifier: Programming Language :: Python :: 3.8
Classifier: Programming Language :: Python :: 3.9
Classifier: Programming Language :: Python :: 3.10
Classifier: Programming Language :: Python :: 3.11
Classifier: Topic :: Scientific/Engineering :: Information Analysis
Classifier: Topic :: Software Development :: Libraries :: Python Modules
Classifier: Topic :: Utilities
Requires-Python: >=3.8
License-File: LICENSE
License-File: AUTHORS.md
Requires-Dist: numpy (<2.0,>=1.23.0)
Requires-Dist: scipy (<2.0,>=1.7.0)
Requires-Dist: globre (<0.2,>=0.1.5)
Requires-Dist: pandas (<3.0,>=1.4.0)
Requires-Dist: xlrd (>=2.0.0)
Requires-Dist: openpyxl (<4.0,>=3.0.0)
Requires-Dist: matplotlib (<4.0,>=3.5.0)
Requires-Dist: bidict (<1.0,>=0.21.0)
Requires-Dist: wheel (<1.0,>=0.40)
Provides-Extra: all
Requires-Dist: spacy (<4.0,>=3.3.0) ; extra == 'all'
Requires-Dist: loky (<4.0,>=3.0.0) ; extra == 'all'
Requires-Dist: PyICU (<3.0,>=2.8) ; extra == 'all'
Requires-Dist: nltk (<3.9,>=3.6.0) ; extra == 'all'
Requires-Dist: scikit-learn (<2.0,>=1.0.0) ; extra == 'all'
Requires-Dist: gensim (<5.0,>=4.1.0) ; extra == 'all'
Requires-Dist: gmpy2 (<3.0,>=2.1.0) ; extra == 'all'
Requires-Dist: rpy2 (<3.6,>=3.5.11) ; extra == 'all'
Requires-Dist: pytest (<8.0,>=7.2.0) ; extra == 'all'
Requires-Dist: hypothesis (<7.0,>=6.49.0) ; extra == 'all'
Requires-Dist: Sphinx (<7.0,>=6.1.0) ; extra == 'all'
Requires-Dist: sphinx-rtd-theme (>=1.2.0) ; extra == 'all'
Requires-Dist: nbsphinx (<1.0,>=0.9.0) ; extra == 'all'
Requires-Dist: coverage (<8.0,>=7.2) ; extra == 'all'
Requires-Dist: coverage-badge (>=1.1.0) ; extra == 'all'
Requires-Dist: pytest-cov (<5.0,>=4.0.0) ; extra == 'all'
Requires-Dist: twine (>=4.0) ; extra == 'all'
Requires-Dist: ipython (>=8.12.0) ; extra == 'all'
Requires-Dist: jupyter (>=1.0.0) ; extra == 'all'
Requires-Dist: notebook (>=6.5.0) ; extra == 'all'
Requires-Dist: tox (<5.0,>=4.4) ; extra == 'all'
Requires-Dist: setuptools (>=67.6) ; extra == 'all'
Provides-Extra: dev
Requires-Dist: coverage (<8.0,>=7.2) ; extra == 'dev'
Requires-Dist: coverage-badge (>=1.1.0) ; extra == 'dev'
Requires-Dist: pytest-cov (<5.0,>=4.0.0) ; extra == 'dev'
Requires-Dist: twine (>=4.0) ; extra == 'dev'
Requires-Dist: ipython (>=8.12.0) ; extra == 'dev'
Requires-Dist: jupyter (>=1.0.0) ; extra == 'dev'
Requires-Dist: notebook (>=6.5.0) ; extra == 'dev'
Requires-Dist: tox (<5.0,>=4.4) ; extra == 'dev'
Requires-Dist: setuptools (>=67.6) ; extra == 'dev'
Provides-Extra: doc
Requires-Dist: Sphinx (<7.0,>=6.1.0) ; extra == 'doc'
Requires-Dist: sphinx-rtd-theme (>=1.2.0) ; extra == 'doc'
Requires-Dist: nbsphinx (<1.0,>=0.9.0) ; extra == 'doc'
Provides-Extra: gensim
Requires-Dist: gensim (<5.0,>=4.1.0) ; extra == 'gensim'
Provides-Extra: lda
Provides-Extra: recommended
Requires-Dist: spacy (<4.0,>=3.3.0) ; extra == 'recommended'
Requires-Dist: loky (<4.0,>=3.0.0) ; extra == 'recommended'
Provides-Extra: rinterop
Requires-Dist: rpy2 (<3.6,>=3.5.11) ; extra == 'rinterop'
Provides-Extra: sklearn
Requires-Dist: scikit-learn (<2.0,>=1.0.0) ; extra == 'sklearn'
Provides-Extra: test
Requires-Dist: pytest (<8.0,>=7.2.0) ; extra == 'test'
Requires-Dist: hypothesis (<7.0,>=6.49.0) ; extra == 'test'
Provides-Extra: textproc
Requires-Dist: spacy (<4.0,>=3.3.0) ; extra == 'textproc'
Requires-Dist: loky (<4.0,>=3.0.0) ; extra == 'textproc'
Provides-Extra: textproc_extra
Requires-Dist: PyICU (<3.0,>=2.8) ; extra == 'textproc_extra'
Requires-Dist: nltk (<3.9,>=3.6.0) ; extra == 'textproc_extra'
Provides-Extra: topic_modeling_eval_extra
Requires-Dist: gmpy2 (<3.0,>=2.1.0) ; extra == 'topic_modeling_eval_extra'
Provides-Extra: wordclouds
